cpumodel/__init__.py
cpumodel/__main__.py
cpumodel/amd.py
cpumodel/cpumodel.py
cpumodel/intel.py
cpumodel-0.0.3.dist-info/METADATA
cpumodel-0.0.3.dist-info/WHEEL
cpumodel-0.0.3.dist-info/entry_points.txt
cpumodel-0.0.3.dist-info/RECORD
