Metadata-Version: 2.1
Name: cpumodel
Version: 0.0.3
Summary: Get info about your CPU
Author: Jonathan Gazeley
Author-email: me@jonathangazeley.com
Requires-Python: >=3.9,<4.0
Classifier: Programming Language :: Python :: 3
Classifier: Programming Language :: Python :: 3.9
Classifier: Programming Language :: Python :: 3.10
Classifier: Programming Language :: Python :: 3.11
Requires-Dist: argparse (>=1.4.0,<2.0.0)
Requires-Dist: py-cpuinfo (>=9.0.0,<10.0.0)
